<?xml version="1.0" encoding="UTF-8"?>
<metadata xml:lang="en"><Esri><CreaDate>20250219</CreaDate><CreaTime>19344600</CreaTime><ArcGISFormat>1.0</ArcGISFormat><SyncOnce>TRUE</SyncOnce><DataProperties><lineage><Process ToolSource="d:\arcgis\desktop10.7\ArcToolbox\Toolboxes\Spatial Analyst Tools.tbx\Kriging" Date="20250219" Time="193446">Kriging elevation_points elevation "C:\Users\nayem\OneDrive\Desktop\ArcGIS Projects\ArcGIS Lab\1. Spatial Interpolation using Kriging-20250219T223429Z-001\surface.tif" "Spherical 123.825248" 20 "VARIABLE 12" #</Process></lineage></DataProperties></Esri></metadata>
